mtools/__init__.py
mtools/version.py
mtools/data/log2code.pickle
mtools/mlaunch/__init__.py
mtools/mlaunch/mlaunch.py
mtools/mlogfilter/__init__.py
mtools/mlogfilter/mlogfilter.py
mtools/mlogfilter/filters/__init__.py
mtools/mlogfilter/filters/base_filter.py
mtools/mlogfilter/filters/datetime_filter.py
mtools/mlogfilter/filters/fast_filter.py
mtools/mlogfilter/filters/logline_filter.py
mtools/mlogfilter/filters/mask_filter.py
mtools/mlogfilter/filters/slow_filter.py
mtools/mlogfilter/filters/tablescan_filter.py
mtools/mlogfilter/filters/transaction_filter.py
mtools/mlogfilter/filters/word_filter.py
mtools/mloginfo/__init__.py
mtools/mloginfo/mloginfo.py
mtools/mloginfo/sections/__init__.py
mtools/mloginfo/sections/base_section.py
mtools/mloginfo/sections/clients_section.py
mtools/mloginfo/sections/connection_section.py
mtools/mloginfo/sections/cursors_section.py
mtools/mloginfo/sections/distinct_section.py
mtools/mloginfo/sections/query_section.py
mtools/mloginfo/sections/restart_section.py
mtools/mloginfo/sections/rs_info_section.py
mtools/mloginfo/sections/rs_state_section.py
mtools/mloginfo/sections/sharding_section.py
mtools/mloginfo/sections/storagestats_section.py
mtools/mloginfo/sections/transactions_section.py
mtools/mplotqueries/__init__.py
mtools/mplotqueries/mplotqueries.py
mtools/mplotqueries/plottypes/__init__.py
mtools/mplotqueries/plottypes/base_type.py
mtools/mplotqueries/plottypes/connchurn_type.py
mtools/mplotqueries/plottypes/event_type.py
mtools/mplotqueries/plottypes/histogram_type.py
mtools/mplotqueries/plottypes/range_type.py
mtools/mplotqueries/plottypes/scatter_type.py
mtools/mtransfer/__init__.py
mtools/mtransfer/mtransfer.py
mtools/test/__init__.py
mtools/test/test_all_help.py
mtools/test/test_all_import.py
mtools/test/test_mlaunch.py
mtools/test/test_mlaunch_commandlines.py
mtools/test/test_mlogfilter.py
mtools/test/test_mloginfo.py
mtools/test/test_mplotqueries.py
mtools/test/test_util_hci.py
mtools/test/test_util_log2code.py
mtools-1.7.2.dist-info/LICENSE.md
mtools-1.7.2.dist-info/METADATA
mtools-1.7.2.dist-info/WHEEL
mtools-1.7.2.dist-info/entry_points.txt
mtools-1.7.2.dist-info/top_level.txt
mtools-1.7.2.dist-info/RECORD
