Metadata-Version: 2.1
Name: mtools
Version: 1.7.2
Summary: Useful scripts to parse and visualize MongoDB log files, launch test environments, and reproduce issues.
Home-page: https://github.com/rueckstiess/mtools
Author: Thomas Rueckstiess
Author-email: thomas@rueckstiess.net
License: Apache 2.0
Keywords: MongoDB logs testing
Platform: UNKNOWN
Classifier: Development Status :: 5 - Production/Stable
Classifier: Intended Audience :: Developers
Classifier: Topic :: Database
Classifier: License :: OSI Approved :: Apache Software License
Classifier: Programming Language :: Python :: 3.7
Classifier: Programming Language :: Python :: 3.8
Classifier: Programming Language :: Python :: 3.9
Classifier: Programming Language :: Python :: 3.10
Provides-Extra: all
Requires-Dist: numpy (>=1.21.6) ; extra == 'all'
Requires-Dist: matplotlib (<4.0.0,>=3.5.3) ; extra == 'all'
Requires-Dist: pymongo (<5.0.0,>=4.3.2) ; extra == 'all'
Requires-Dist: psutil (<6.0.0,>=5.9.3) ; extra == 'all'
Requires-Dist: packaging (>=21.3) ; extra == 'all'
Requires-Dist: python-dateutil (<3.0.0,>=2.8.2) ; extra == 'all'
Provides-Extra: mlaunch
Requires-Dist: pymongo (<5.0.0,>=4.3.2) ; extra == 'mlaunch'
Requires-Dist: psutil (<6.0.0,>=5.9.3) ; extra == 'mlaunch'
Requires-Dist: packaging (>=21.3) ; extra == 'mlaunch'
Requires-Dist: python-dateutil (<3.0.0,>=2.8.2) ; extra == 'mlaunch'
Provides-Extra: mlogfilter
Requires-Dist: python-dateutil (<3.0.0,>=2.8.2) ; extra == 'mlogfilter'
Provides-Extra: mloginfo
Requires-Dist: numpy (>=1.21.6) ; extra == 'mloginfo'
Requires-Dist: python-dateutil (<3.0.0,>=2.8.2) ; extra == 'mloginfo'
Provides-Extra: mplotqueries
Requires-Dist: numpy (>=1.21.6) ; extra == 'mplotqueries'
Requires-Dist: matplotlib (<4.0.0,>=3.5.3) ; extra == 'mplotqueries'
Requires-Dist: python-dateutil (<3.0.0,>=2.8.2) ; extra == 'mplotqueries'
Provides-Extra: mtransfer
Requires-Dist: pymongo (<5.0.0,>=4.3.2) ; extra == 'mtransfer'
Requires-Dist: wiredtiger (>=3.2.1) ; extra == 'mtransfer'
Requires-Dist: python-dateutil (<3.0.0,>=2.8.2) ; extra == 'mtransfer'
